pytrack_analysis/__init__.py
pytrack_analysis/_globals.py
pytrack_analysis/benchmark.py
pytrack_analysis/database.py
pytrack_analysis/kinematics.py
pytrack_analysis/logger.py
pytrack_analysis/preprocessing.py
pytrack_analysis/profile.py
pytrack_analysis-0.0.3.dist-info/DESCRIPTION.rst
pytrack_analysis-0.0.3.dist-info/METADATA
pytrack_analysis-0.0.3.dist-info/RECORD
pytrack_analysis-0.0.3.dist-info/WHEEL
pytrack_analysis-0.0.3.dist-info/metadata.json
pytrack_analysis-0.0.3.dist-info/top_level.txt
tests/__init__.py
tests/broken.py
tests/test_integrity.py
tests/test_kinematics.py
tests/test_log.py
tests/test_profile.py
