Metadata-Version: 1.2
Name: pytrack-analysis
Version: 0.0.3
Summary: Toolbox for analyzing object centroid data with Python.
Home-page: https://pypi.python.org/pypi/pytrack-analysis
Author: Dennis Goldschmidt
Author-email: dennis.goldschmidt@neuro.fchampalimaud.org
License: GPLv3
Keywords: tracking,data analysis,fly
Platform: Windows10Pro
Platform: MacOSX-ElCapitan
Classifier: Development Status :: 1 - Planning
Classifier: Operating System :: MacOS :: MacOS X
Classifier: Topic :: Utilities
Classifier: License :: OSI Approved :: GNU General Public License v3 (GPLv3)
Classifier: Programming Language :: Python :: 3.6
Requires-Python: >=3.6
